{
  "generator-jhipster": {
    "applicationType": "monolith",
    "authenticationType": "oauth2",
    "baseName": "fenyaTMS",
    "blueprints": [],
    "buildTool": "maven",
    "cacheProvider": "ehcache",
    "clientFramework": "angularX",
    "clientPackageManager": "npm",
    "clientTheme": "none",
    "clientThemeVariant": "",
    "creationTimestamp": 1678983969918,
    "databaseType": "sql",
    "devDatabaseType": "postgresql",
    "devServerPort": 4200,
    "dtoSuffix": "DTO",
    "enableGradleEnterprise": false,
    "enableHibernateCache": true,
    "enableSwaggerCodegen": "true",
    "enableTranslation": true,
    "entitySuffix": "",
    "gitCompany": "",
    "jhiPrefix": "jhi",
    "jhipsterVersion": "7.9.3",
    "languages": ["en"],
    "messageBroker": "kafka",
    "nativeLanguage": "en",
    "otherModules": [],
    "packageFolder": "com/fenya/tms",
    "packageName": "com.fenya.tms",
    "pages": [],
    "prodDatabaseType": "postgresql",
    "reactive": false,
    "searchEngine": "elasticsearch",
    "serverPort": 8080,
    "serviceDiscoveryType": "eureka",
    "skipCheckLengthOfIdentifier": false,
    "skipClient": false,
    "skipFakeData": false,
    "skipUserManagement": true,
    "testFrameworks": [],
    "useSass": true,
    "websocket": false,
    "withAdminUi": true
  },
  "git-provider": "GitHub",
  "git-company": "FenyaTransport",
  "repository-name": "jhipster-fenya-tms"
}
